README.txt
conf.py
index.txt
setup.cfg
setup.py
docs/CLASSES.txt
docs/HISTORY.txt
docs/LICENSE.GPL
docs/LICENSE.txt
kcrw/__init__.py
kcrw.nprapi.egg-info/PKG-INFO
kcrw.nprapi.egg-info/SOURCES.txt
kcrw.nprapi.egg-info/dependency_links.txt
kcrw.nprapi.egg-info/entry_points.txt
kcrw.nprapi.egg-info/namespace_packages.txt
kcrw.nprapi.egg-info/not-zip-safe
kcrw.nprapi.egg-info/requires.txt
kcrw.nprapi.egg-info/top_level.txt
kcrw/nprapi/__init__.py
kcrw/nprapi/mapping.txt
kcrw/nprapi/mocks.py
kcrw/nprapi/story.py
kcrw/nprapi/story.txt
kcrw/nprapi/tests.py