Metadata-Version: 1.0
Name: kcrw.nprapi
Version: 1.0b3
Summary: A python library for using National Public Radio's API (http://www.npr.org/api/index)
Home-page: http://svn.plone.org/svn/collective/
Author: UNKNOWN
Author-email: UNKNOWN
License: GPL
Platform: UNKNOWN
Classifier: Programming Language :: Python
